chik_base/__init__.py
chik_base/py.typed
chik_base/atoms/__init__.py
chik_base/atoms/hexbytes.py
chik_base/atoms/ints.py
chik_base/atoms/sized_bytes.py
chik_base/atoms/struct_stream.py
chik_base/bls12_381/__init__.py
chik_base/bls12_381/bls_public_key.py
chik_base/bls12_381/bls_secret_exponent.py
chik_base/bls12_381/bls_signature.py
chik_base/bls12_381/secret_key_utils.py
chik_base/cbincode/__init__.py
chik_base/cbincode/parser.py
chik_base/cbincode/streamer.py
chik_base/cbincode/util.py
chik_base/contrib/__init__.py
chik_base/contrib/bech32m.py
chik_base/core/__init__.py
chik_base/core/coin.py
chik_base/core/coin_spend.py
chik_base/core/conlang.py
chik_base/core/spend_bundle.py
chik_base/meta/__init__.py
chik_base/meta/optional.py
chik_base/meta/type_tree.py
chik_base/meta/typing.py
chik_base/util/__init__.py
chik_base/util/bech32.py
chik_base/util/std_hash.py
chik_base-0.1.7.dist-info/LICENSE
chik_base-0.1.7.dist-info/METADATA
chik_base-0.1.7.dist-info/WHEEL
chik_base-0.1.7.dist-info/top_level.txt
chik_base-0.1.7.dist-info/RECORD
