Metadata-Version: 2.1
Name: chik-base
Version: 0.1.7
Summary: Common types and simple utilities used through chik code base
Author-email: Richard Kiss <him@richardkiss.com>
License: Apache-2.0
Project-URL: Repository, https://github.com/Chik-Network/chik_base.git
License-File: LICENSE
Requires-Dist: klvm-rs ==0.2.5
Requires-Dist: chik-rs >=0.5.2
Provides-Extra: dev
Requires-Dist: ruff >=0.0.252 ; extra == 'dev'
Requires-Dist: black >=23.1.0 ; extra == 'dev'
Requires-Dist: pytest >=7.2.1 ; extra == 'dev'
